2024/12feb/graytobin.v
module graytobin(gray, binary);
  input  [2:0] gray;
  output [2:0] binary;

  assign binary[0] = gray[2] ^ gray[1] ^ gray[0];
  assign binary[1] = gray[2] ^ gray[1];
  assign binary[2] = gray[2];

endmodule

2024/12feb/graytobin_tb.v
module graytobin_tb;

  reg  [2:0] gray;
  wire [2:0] binary;

  graytobin inst(gray, binary);

  initial begin
    $monitor("Gray = %b --> Binary = %b", gray, binary);
    $dumpfile("graytobin_sim.vcd");
    $dumpvars;

    gray = 3'b000; #1;
    gray = 3'b001; #1;
    gray = 3'b011; #1;
    gray = 3'b010; #1;
    gray = 3'b110; #1;
    gray = 3'b111; #1;
    gray = 3'b101; #1;
    gray = 3'b100; #1;
  end

endmodule

2024/12feb/graytobin_sim.vcd
$date
	Mon Feb 12 11:51:15 2024
$end
$version
	Icarus Verilog
$end
$timescale
	1s
$end
$scope module graytobin_tb $end
$var wire 3 ! binary [2:0] $end
$var reg 3 " gray [2:0] $end
$scope module inst $end
$var wire 3 # binary [2:0] $end
$var wire 3 $ gray [2:0] $end
$upscope $end
$upscope $end
$enddefinitions $end
#0
$dumpvars
b0 $
b0 #
b0 "
b0 !
$end
#1
b1 !
b1 #
b1 "
b1 $
#2
b10 !
b10 #
b11 "
b11 $
#3
b11 !
b11 #
b10 "
b10 $
#4
b100 !
b100 #
b110 "
b110 $
#5
b101 !
b101 #
b111 "
b111 $
#6
b110 !
b110 #
b101 "
b101 $
#7
b111 !
b111 #
b100 "
b100 $
