2024/01apr/quesone.v
module quesone (
  input A,
  input B,
  input C,
  output F
);

  // Data lines for the multiplexer
  wire d0, d1, d2, d3;

  // Logic for data lines based on minterms
  assign d0 = ~A & ~B & ~C;  // Minterm 3
  assign d1 = ~A & ~B & C;    // Minterm 5
  assign d2 = ~A & B & C;     // Minterm 6
  assign d3 = A & ~B & C;     // Minterm 7

  // Select lines for the multiplexer (B is MSB, C is LSB)
  assign F = (B & C) ? d3 :  // When BC = 11
             (B & ~C) ? d2 :  // When BC = 10
                         (~B & C) ? d1 :  // When BC = 01
                                      d0;   // When BC = 00

endmodule

2024/01apr/quesone_tb.v
module quesone_tb;

  // Inputs for the F_function module
  reg A, B, C;

  // Output from the F_function module
  wire F;

  // Instantiate the F_function module
  quesone dut (A, B, C, F);

  initial begin
    // Apply all possible input combinations
    $display("A B C | F");
    $display("-------");
    $monitor("%b %b %b | %b", A, B, C, F);
    $dumpfile("quesone_sim.vcd");
    $dumpvars;

    A = 0; B = 0; C = 0; #10;
    A = 0; B = 0; C = 1; #10;
    A = 0; B = 1; C = 0; #10;
    A = 0; B = 1; C = 1; #10;
    A = 1; B = 0; C = 0; #10;
    A = 1; B = 0; C = 1; #10;
    A = 1; B = 1; C = 0; #10;
    A = 1; B = 1; C = 1; #10;

    $finish;
  end

endmodule

2024/01apr/quesone_sim.vcd
$date
	Mon Apr 01 10:52:21 2024
$end
$version
	Icarus Verilog
$end
$timescale
	1s
$end
$scope module quesone_tb $end
$var wire 1 ! F $end
$var reg 1 " A $end
$var reg 1 # B $end
$var reg 1 $ C $end
$scope module dut $end
$var wire 1 % A $end
$var wire 1 & B $end
$var wire 1 ' C $end
$var wire 1 ! F $end
$var wire 1 ( d0 $end
$var wire 1 ) d1 $end
$var wire 1 * d2 $end
$var wire 1 + d3 $end
$upscope $end
$upscope $end
$enddefinitions $end
#0
$dumpvars
0+
0*
0)
1(
0'
0&
0%
0$
0#
0"
1!
$end
#10
0(
1)
1$
1'
#20
0!
0)
0$
0'
1#
1&
#30
1*
1$
1'
#40
0*
0$
0'
0#
0&
1"
1%
#50
1+
1$
1'
#60
0+
0$
0'
1#
1&
#70
1$
1'
