2024/01apr/quesfour.v
module quesfour (
  input D7,
  input D6,
  input D5,
  input D4,
  input D3,
  input D2,
  input D1,
  input D0,
  output reg [2:0] Y
);

  always @(*) begin
    // Assign default value (no active input)
    Y = 3'b000;

    // Check for active inputs with priority (highest to lowest)
    if (D7) begin
      Y = 3'b111;  // D7 has highest priority
    end else if (D6) begin
      Y = 3'b110;
    end else if (D5) begin
      Y = 3'b101;
    end else if (D4) begin
      Y = 3'b100;
    end else if (D3) begin
      Y = 3'b011;
    end else if (D2) begin
      Y = 3'b010;
    end else if (D1) begin
      Y = 3'b001;
    end else if (D0) begin
      Y = 3'b000;  // D0 has lowest priority (already assigned as default)
    end
  end

endmodule

2024/01apr/quesfour_tb.v
module quesfour_tb;

  // Inputs for the encoder8to3 module
  reg D7, D6, D5, D4, D3, D2, D1, D0;

  // Outputs from the encoder8to3 module
  wire [2:0] Y;

  // Instantiate the encoder8to3 module
  quesfour dut (D7, D6, D5, D4, D3, D2, D1, D0, Y);

  initial begin
    // Apply all possible input combinations
    $display("D7 D6 D5 D4 D3 D2 D1 D0 | Y2 Y1 Y0");
    $display("------------------------| --------");
    $monitor("%b %b %b %b %b %b %b %b | %b %b %b", D7, D6, D5, D4, D3, D2, D1, D0, Y[2], Y[1], Y[0]);
    $dumpfile("quesfour_sim.vcd");
    $dumpvars;

    // Test cases covering single active inputs with priority
    D7 = 0; D6 = 0; D5 = 0; D4 = 0; D3 = 0; D2 = 0; D1 = 0; D0 = 1; #10;  // D0 (lowest priority)
    D7 = 0; D6 = 0; D5 = 0; D4 = 0; D3 = 0; D2 = 0; D1 = 1; D0 = 0; #10;  // D1
    D7 = 0; D6 = 0; D5 = 0; D4 = 0; D3 = 0; D2 = 1; D1 = 0; D0 = 0; #10;  // D2
    D7 = 0; D6 = 0; D5 = 0; D4 = 0; D3 = 1; D2 = 0; D1 = 0; #10;  // D3
    D7 = 0; D6 = 0; D5 = 0; D4 = 1; D3 = 0; D2 = 0; D1 = 0; #10;  // D4
    D7 = 0; D6 = 0; D5 = 1; D4 = 0; D3 = 0; D2 = 0; D1 = 0; #10;  // D5
    D7 = 0; D6 = 1; D5 = 0; D4 = 0; D3 = 0; D2 = 0; D1 = 0; #10;  // D6 (highest priority)
    D7 = 1; D6 = 0; D5 = 0; D4 = 0; D3 = 0; D2 = 0; D1 = 0; D0 = 0; #10;  // D7 (highest priority) - overrides lower active inputs

    // Test case for multiple active inputs (undefined behavior - X)
    D7 = 1; D6 = 0; D5 = 1; D4 = 0; D3 = 0; D2 = 0; D1 = 0; D0 = 0; #10;  // Multiple active inputs (X)

    $finish;
  end

endmodule

2024/01apr/quesfour_sim.vcd
$date
	Mon Apr 01 11:54:06 2024
$end
$version
	Icarus Verilog
$end
$timescale
	1s
$end
$scope module quesfour_tb $end
$var wire 3 ! Y [2:0] $end
$var reg 1 " D0 $end
$var reg 1 # D1 $end
$var reg 1 $ D2 $end
$var reg 1 % D3 $end
$var reg 1 & D4 $end
$var reg 1 ' D5 $end
$var reg 1 ( D6 $end
$var reg 1 ) D7 $end
$scope module dut $end
$var wire 1 * D0 $end
$var wire 1 + D1 $end
$var wire 1 , D2 $end
$var wire 1 - D3 $end
$var wire 1 . D4 $end
$var wire 1 / D5 $end
$var wire 1 0 D6 $end
$var wire 1 1 D7 $end
$var reg 3 2 Y [2:0] $end
$upscope $end
$upscope $end
$enddefinitions $end
#0
$dumpvars
b0 2
01
00
0/
0.
0-
0,
0+
1*
0)
0(
0'
0&
0%
0$
0#
1"
b0 !
$end
#10
b1 2
b1 !
0"
0*
1#
1+
#20
b10 2
b10 !
0#
0+
1$
1,
#30
b11 2
b11 !
0$
0,
1%
1-
#40
b100 2
b100 !
0%
0-
1&
1.
#50
b101 2
b101 !
0&
0.
1'
1/
#60
b110 2
b110 !
0'
0/
1(
10
#70
b111 2
b111 !
0(
00
1)
11
#80
b111 2
b111 !
1'
1/
