2024/01apr/questhree.v
module questhree (
  input A2,
  input A1,
  input A0,
  output reg [7:0] Y
);

  always @(*) begin
    // Assign each output based on the input combination
    Y[0] <= ~A2 & ~A1 & ~A0;  // Y0 is active when A2, A1, and A0 are all low
    Y[1] <= ~A2 & ~A1 & A0;    // Y1 is active when A2 and A1 are low, A0 is high
    Y[2] <= ~A2 & A1 & ~A0;    // Y2 is active when A2 is low, A1 is high, A0 is low
    Y[3] <= ~A2 & A1 & A0;     // Y3 is active when A2 is low, A1 and A0 are high
    Y[4] <= A2 & ~A1 & ~A0;    // Y4 is active when A2 is high, A1 is low, A0 is low
    Y[5] <= A2 & ~A1 & A0;     // Y5 is active when A2 is high, A1 is low, A0 is high
    Y[6] <= A2 & A1 & ~A0;     // Y6 is active when A2 and A1 are high, A0 is low
    Y[7] <= A2 & A1 & A0;      // Y7 is active when A2 and A1 are high, A0 is high
  end

endmodule

2024/01apr/questhree_tb.v
module questhree_tb;

  // Inputs for the decoder3to8 module
  reg A2, A1, A0;

  // Outputs from the decoder3to8 module
  wire [7:0] Y;

  // Instantiate the decoder3to8 module
  questhree dut (A2, A1, A0, Y);

  initial begin
    // Apply all possible input combinations
    $display("A2 A1 A0 | Y7 Y6 Y5 Y4 Y3 Y2 Y1 Y0");
    $display("---------| -------- -------- --------");
    $monitor("%b %b %b | %b %b %b %b %b %b %b %b", A2, A1, A0, Y[7], Y[6], Y[5], Y[4], Y[3], Y[2], Y[1], Y[0]);
    $dumpfile("questhree_sim.vcd");
    $dumpvars;

    A2 = 0; A1 = 0; A0 = 0; #10;
    A2 = 0; A1 = 0; A0 = 1; #10;
    A2 = 0; A1 = 1; A0 = 0; #10;
    A2 = 0; A1 = 1; A0 = 1; #10;
    A2 = 1; A1 = 0; A0 = 0; #10;
    A2 = 1; A1 = 0; A0 = 1; #10;
    A2 = 1; A1 = 1; A0 = 0; #10;
    A2 = 1; A1 = 1; A0 = 1; #10;

    $finish;
  end

endmodule

2024/01apr/questhree_sim.vcd
$date
	Mon Apr 01 11:40:25 2024
$end
$version
	Icarus Verilog
$end
$timescale
	1s
$end
$scope module questhree_tb $end
$var wire 8 ! Y [7:0] $end
$var reg 1 " A0 $end
$var reg 1 # A1 $end
$var reg 1 $ A2 $end
$scope module dut $end
$var wire 1 % A0 $end
$var wire 1 & A1 $end
$var wire 1 ' A2 $end
$var reg 8 ( Y [7:0] $end
$upscope $end
$upscope $end
$enddefinitions $end
#0
$dumpvars
b1 (
0'
0&
0%
0$
0#
0"
b1 !
$end
#10
b10 (
b10 !
1"
1%
#20
b100 !
b100 (
0"
0%
1#
1&
#30
b1000 !
b1000 (
1"
1%
#40
b10000 !
b10000 (
0"
0%
0#
0&
1$
1'
#50
b100000 !
b100000 (
1"
1%
#60
b1000000 !
b1000000 (
0"
0%
1#
1&
#70
b10000000 !
b10000000 (
1"
1%
