2024/08apr/quesfour.v
module quesfour(
  input A,
  input B,
  input C,
  output reg D0,
  output reg D1,
  output reg D2,
  output reg D3,
  output reg D4,
  output reg D5,
  output reg D6,
  output reg D7
);

  always @(*) begin
    case ({A, B, C})
      3'b000: begin D0 = 1'b1; D1 = 1'b0; D2 = 1'b0; D3 = 1'b0; D4 = 1'b0; D5 = 1'b0; D6 = 1'b0; D7 = 1'b0; end
      3'b001: begin D0 = 1'b0; D1 = 1'b0; D2 = 1'b0; D3 = 1'b0; D4 = 1'b0; D5 = 1'b0; D6 = 1'b1; D7 = 1'b0; end
      3'b010: begin D0 = 1'b0; D1 = 1'b0; D2 = 1'b0; D3 = 1'b0; D4 = 1'b1; D5 = 1'b0; D6 = 1'b0; D7 = 1'b0; end
      3'b011: begin D0 = 1'b0; D1 = 1'b0; D2 = 1'b0; D3 = 1'b1; D4 = 1'b0; D5 = 1'b0; D6 = 1'b0; D7 = 1'b0; end
      3'b100: begin D0 = 1'b0; D1 = 1'b0; D2 = 1'b1; D3 = 1'b0; D4 = 1'b0; D5 = 1'b0; D6 = 1'b0; D7 = 1'b0; end
      3'b101: begin D0 = 1'b0; D1 = 1'b1; D2 = 1'b0; D3 = 1'b0; D4 = 1'b0; D5 = 1'b0; D6 = 1'b0; D7 = 1'b0; end
      3'b110: begin D0 = 1'b1; D1 = 1'b0; D2 = 1'b0; D3 = 1'b0; D4 = 1'b0; D5 = 1'b0; D6 = 1'b0; D7 = 1'b0; end
      3'b111: begin D0 = 1'b0; D1 = 1'b0; D2 = 1'b0; D3 = 1'b0; D4 = 1'b0; D5 = 1'b0; D6 = 1'b0; D7 = 1'b0; end
    endcase
  end

endmodule

2024/08apr/quesfour_tb.v
module quesfour_tb;

  // Inputs
  reg A;
  reg B;
  reg C;

  // Outputs
  wire D0;
  wire D1;
  wire D2;
  wire D3;
  wire D4;
  wire D5;
  wire D6;
  wire D7;

  // Instantiate the decoder3to8 module
  quesfour quesfour (
    .A(A),
    .B(B),
    .C(C),
    .D0(D0),
    .D1(D1),
    .D2(D2),
    .D3(D3),
    .D4(D4),
    .D5(D5),
    .D6(D6),
    .D7(D7)
  );

  // Initial values
  initial begin
    A = 0;
    B = 0;
    C = 0;
  end

  // Test vectors
  initial begin
    $dumpfile("quesfour_sim.vcd");
    $dumpvars;
    #10 A = 0; B = 0; C = 0;
    #10 A = 0; B = 0; C = 1;
    #10 A = 0; B = 1; C = 0;
    #10 A = 0; B = 1; C = 1;
    #10 A = 1; B = 0; C = 0;
    #10 A = 1; B = 0; C = 1;
    #10 A = 1; B = 1; C = 0;
    #10 A = 1; B = 1; C = 1;
    #10 $finish;
  end

endmodule

2024/08apr/quesfour_sim.vcd
$date
	Mon Apr 08 11:44:30 2024
$end
$version
	Icarus Verilog
$end
$timescale
	1s
$end
$scope module quesfour_tb $end
$var wire 1 ! D0 $end
$var wire 1 " D1 $end
$var wire 1 # D2 $end
$var wire 1 $ D3 $end
$var wire 1 % D4 $end
$var wire 1 & D5 $end
$var wire 1 ' D6 $end
$var wire 1 ( D7 $end
$var reg 1 ) A $end
$var reg 1 * B $end
$var reg 1 + C $end
$scope module quesfour $end
$var wire 1 , A $end
$var wire 1 - B $end
$var wire 1 . C $end
$var reg 1 / D0 $end
$var reg 1 0 D1 $end
$var reg 1 1 D2 $end
$var reg 1 2 D3 $end
$var reg 1 3 D4 $end
$var reg 1 4 D5 $end
$var reg 1 5 D6 $end
$var reg 1 6 D7 $end
$upscope $end
$upscope $end
$enddefinitions $end
#0
$dumpvars
06
05
04
03
02
01
00
1/
0.
0-
0,
0+
0*
0)
0(
0'
0&
0%
0$
0#
0"
1!
$end
#20
15
1'
0/
0!
1+
1.
#30
05
0'
13
1%
0+
0.
1*
1-
#40
03
0%
12
1$
1+
1.
#50
02
0$
11
1#
0+
0.
0*
0-
1)
1,
#60
01
0#
10
1"
1+
1.
#70
00
0"
1/
1!
0+
0.
1*
1-
#80
0/
0!
1+
1.
