2024/05feb/questhree.v
module questhree(
    input A,
    input B,
    input C,
    output Y
);

assign Y = ((~A)&&C) || (A&&(~B));

endmodule

2024/05feb/questhree_tb.v
module questhree_tb;

reg A;
reg B;
reg C;
wire Y;

questhree inst(
    .A(A),
    .B(B),
    .C(C),
    .Y(Y)
);

initial begin
    $dumpfile("questhree_sim.vcd");
    $dumpvars;
    A = 0; C = 0; B = 0;
    #10;
    A = 0; C = 0; B = 1;
    #10;
    A = 0; C = 1; B = 0;
    #10;
    A = 0; C = 1; B = 1;
    #10;
    A = 1; C = 0; B = 0;
    #10;
    A = 1; C = 0; B = 1;
    #10;
    A = 1; C = 1; B = 0;
    #10;
    A = 1; C = 1; B = 1;
    #10;

    $finish;
end

endmodule

2024/05feb/questhree_sim.vcd
$date
	Mon Feb 05 12:38:17 2024
$end
$version
	Icarus Verilog
$end
$timescale
	1s
$end
$scope module questhree_tb $end
$var wire 1 ! Y $end
$var reg 1 " A $end
$var reg 1 # B $end
$var reg 1 $ C $end
$scope module inst $end
$var wire 1 % A $end
$var wire 1 & B $end
$var wire 1 ' C $end
$var wire 1 ! Y $end
$upscope $end
$upscope $end
$enddefinitions $end
#0
$dumpvars
0'
0&
0%
0$
0#
0"
0!
$end
#10
1#
1&
#20
1!
0#
0&
1$
1'
#30
1#
1&
#40
1!
0#
0&
0$
0'
1"
1%
#50
0!
1#
1&
#60
1!
0#
0&
1$
1'
#70
0!
1#
1&
