2024/Project Arihant/one.v
module one (
  input [7:0] A,
  input [7:0] B,
  input [3:0] Opcode,
  output reg [7:0] Result,
  output reg Zero,
  output reg CarryOut
);

  // Define operations
  localparam ADD  = 4'b0000;
  localparam SUB  = 4'b0001;
  localparam AND  = 4'b0010;
  localparam OR   = 4'b0011;
  localparam XOR  = 4'b0100;
  localparam NOT  = 4'b0101;  // One's complement (invert)
  localparam SLL  = 4'b0110;  // Shift Left
  localparam SRL  = 4'b0111;  // Shift Right Logical
  localparam SRA  = 4'b1000;  // Shift Right Arithmetic

  always @(A or B or Opcode) begin
    case (Opcode)
      ADD: begin
        Result = A + B;
        CarryOut = (A[7] ^ B[7]) & (A[7] ^ Result[7]);
      end
      SUB: begin
        Result = A - B;
        CarryOut = ~A[7] & B[7] | A[7] & ~Result[7];
      end
      AND: Result = A & B;
      OR:  Result = A | B;
      XOR: Result = A ^ B;
      NOT: Result = ~A;  // Invert all bits
      SLL: Result = A << B[2:0];  // Shift Left by lower 3 bits of B
      SRL: Result = A >> B[2:0];  // Shift Right Logical by lower 3 bits of B
      SRA: Result = A >>> B[2:0]; // Shift Right Arithmetic by lower 3 bits of B
      default: Result = 8'bX;  // Set result to unknown (X) for invalid opcode
    endcase
    Zero = (Result == 8'b0);  // Check for zero output
  end

endmodule

2024/Project Arihant/one_tb.v
module one_tb;

  reg [7:0] A, B;
  reg [3:0] Opcode;
  wire [7:0] Result;
  wire Zero, CarryOut;

  one ONE (A, B, Opcode, Result, Zero, CarryOut);

  initial begin
    $dumpfile("one_sim.vcd");
    $dumpvars;
    // Test addition with different values
    A = 8'd5; B = 8'd3; Opcode = 4'b0000;
    #10;
    $display("A = %d, B = %d, Opcode = ADD, Result = %d, Zero = %b, CarryOut = %b", A, B, Result, Zero, CarryOut);

    A = 8'd255; B = 8'd1; Opcode = 4'b0000;
    #10;
    $display("A = %d, B = %d, Opcode = ADD, Result = %d, Zero = %b, CarryOut = %b", A, B, Result, Zero, CarryOut);

    // Test subtraction with different values (check for borrow)
    A = 8'd5; B = 8'd8; Opcode = 4'b0001;
    #10;
    $display("A = %d, B = %d, Opcode = SUB, Result = %d, Zero = %b, CarryOut = %b", A, B, Result, Zero, CarryOut);

    A = 8'd0; B = 8'd1; Opcode = 4'b0001;
    #10;
    $display("A = %d, B = %d, Opcode = SUB, Result = %d, Zero = %b, CarryOut = %b", A, B, Result, Zero, CarryOut);

    // Test logical operations
    A = 8'b10101010; B = 8'b01010101; Opcode = 4'b0010; #10;
    $display("A = %b, B = %b, Opcode = AND, Result = %b, Zero = %b, CarryOut = %b", A, B, Result, Zero, CarryOut);

    A = 8'b10101010; B = 8'b01010101; Opcode = 4'b0011; #10;
    $display("A = %b, B = %b, Opcode = OR, Result = %b, Zero = %b, CarryOut = %b", A, B, Result, Zero, CarryOut);

    A = 8'b10101010; B = 8'b01010101; Opcode = 4'b0100; #10;
    $display("A = %b, B = %b, Opcode = XOR, Result = %b, Zero = %b, CarryOut = %b", A, B, Result, Zero, CarryOut);

    // Test one's complement (NOT)
    A = 8'b10101010; Opcode = 4'b0101; #10;
    $display("A = %b, Opcode = NOT, Result = %b, Zero = %b, CarryOut = %b", A, Result, Zero, CarryOut);

    // Test shift operations with different values
    A = 8'b10101010; B = 8'd2; Opcode = 4'b0110; #10
    $display("A = %b, B = %d, Opcode = SLL, Result = %b, Zero = %b, CarryOut = %b", A, B, Result, Zero, CarryOut);
    
  end

endmodule

2024/Project Arihant/one_sim.vcd
$date
	Sat Apr 13 18:51:26 2024
$end
$version
	Icarus Verilog
$end
$timescale
	1s
$end
$scope module one_tb $end
$var wire 1 ! CarryOut $end
$var wire 8 " Result [7:0] $end
$var wire 1 # Zero $end
$var reg 8 $ A [7:0] $end
$var reg 8 % B [7:0] $end
$var reg 4 & Opcode [3:0] $end
$scope module ONE $end
$var wire 8 ' A [7:0] $end
$var wire 8 ( B [7:0] $end
$var wire 4 ) Opcode [3:0] $end
$var reg 1 * CarryOut $end
$var reg 8 + Result [7:0] $end
$var reg 1 , Zero $end
$upscope $end
$upscope $end
$enddefinitions $end
#0
$dumpvars
0,
b1000 +
0*
b0 )
b11 (
b101 '
b0 &
b11 %
b101 $
0#
b1000 "
0!
$end
#10
1,
1#
1*
1!
b0 +
b0 "
b1 %
b1 (
b11111111 $
b11111111 '
#20
0,
0#
0*
0!
b11111101 +
b11111101 "
b1 &
b1 )
b1000 %
b1000 (
b101 $
b101 '
#30
b11111111 +
b11111111 "
b1 %
b1 (
b0 $
b0 '
#40
1,
1#
b0 +
b0 "
b10 &
b10 )
b1010101 %
b1010101 (
b10101010 $
b10101010 '
#50
0,
0#
b11111111 +
b11111111 "
b11 &
b11 )
#60
b100 &
b100 )
#70
b1010101 +
b1010101 "
b101 &
b101 )
#80
b10101000 +
b10101000 "
b110 &
b110 )
b10 %
b10 (
