2024/19feb/quesfour.v
module quesfour(
    input P,
    input Q,
    input R,
    output S,
    output C
);

assign S = (P^(Q^R));
assign C = ((P&&Q) || (Q&&R) || (P&&R));

endmodule

2024/19feb/quesfour_tb.v
module quesfour_tb;

reg P,Q,R;
wire S,C;

quesfour inst(
    .P(P),
    .Q(Q),
    .R(R),
    .S(S),
    .C(C)
);

initial begin
    $dumpfile("quesfour_sim.vcd");
    $dumpvars;

    P = 0; Q = 0; R = 0;
    #10;
    P = 0; Q = 0; R = 1;
    #10;
    P = 0; Q = 1; R = 0;
    #10;
    P = 0; Q = 1; R = 1;
    #10;
    P = 1; Q = 0; R = 0;
    #10;
    P = 1; Q = 0; R = 1;
    #10;
    P = 1; Q = 1; R = 0;
    #10;
    P = 1; Q = 1; R = 1;
    #10;

    $finish;

end
endmodule

2024/19feb/quesfour_sim.vcd
$date
	Mon Feb 19 12:05:14 2024
$end
$version
	Icarus Verilog
$end
$timescale
	1s
$end
$scope module quesfour_tb $end
$var wire 1 ! C $end
$var wire 1 " S $end
$var reg 1 # P $end
$var reg 1 $ Q $end
$var reg 1 % R $end
$scope module inst $end
$var wire 1 ! C $end
$var wire 1 & P $end
$var wire 1 ' Q $end
$var wire 1 ( R $end
$var wire 1 " S $end
$upscope $end
$upscope $end
$enddefinitions $end
#0
$dumpvars
0(
0'
0&
0%
0$
0#
0"
0!
$end
#10
1"
1%
1(
#20
0%
0(
1$
1'
#30
1!
0"
1%
1(
#40
0!
1"
0%
0(
0$
0'
1#
1&
#50
0"
1!
1%
1(
#60
0%
0(
1$
1'
#70
1"
1%
1(
