2024/18feb/quesfive.v
module quesfive (
  input A,
  input B,
  input C,
  output F
);

  // Data lines for the multiplexer
  wire d0, d1, d2, d3;

  // Assign values to data lines based on the function definition
  assign d0 = C;  // Σ(3)
  assign d1 = ~A;  // Σ(5)
  assign d2 = A & ~C; // Σ(6)
  assign d3 = ~A & ~C; // Σ(7)

  // Select lines for the multiplexer (AB selects between d0-d3)
  assign F = (A & ~B) ? d0 :  // When AB = 00
             (~A & B) ? d1 :  // When AB = 01
             (A & B) ? d2 :    // When AB = 10
                         d3;    // When AB = 11

endmodule

2024/18feb/quesfive_tb.v
module quesfive_tb;

  reg A, B, C;
  wire F;

  // Instantiate the F_function module
  quesfive dut (A, B, C, F);

  initial begin
    // Apply all possible input combinations with a delay
    $dumpfile("quesfive_sim.vcd");
    $dumpvars;
    $display("A B C | F");
    $display("-------");
    $monitor("%b %b %b | %b", A, B, C, F);

    A = 0; B = 0; C = 0; #10;
    A = 0; B = 0; C = 1; #10;
    A = 0; B = 1; C = 0; #10;
    A = 0; B = 1; C = 1; #10;
    A = 1; B = 0; C = 0; #10;
    A = 1; B = 0; C = 1; #10;
    A = 1; B = 1; C = 0; #10;
    A = 1; B = 1; C = 1; #10;

    $finish;
  end

endmodule

2024/18feb/quesfive_sim.vcd
$date
	Mon Mar 18 11:57:48 2024
$end
$version
	Icarus Verilog
$end
$timescale
	1s
$end
$scope module quesfive_tb $end
$var wire 1 ! F $end
$var reg 1 " A $end
$var reg 1 # B $end
$var reg 1 $ C $end
$scope module dut $end
$var wire 1 % A $end
$var wire 1 & B $end
$var wire 1 ' C $end
$var wire 1 ! F $end
$var wire 1 ( d0 $end
$var wire 1 ) d1 $end
$var wire 1 * d2 $end
$var wire 1 + d3 $end
$upscope $end
$upscope $end
$enddefinitions $end
#0
$dumpvars
1+
0*
1)
0(
0'
0&
0%
0$
0#
0"
1!
$end
#10
0!
0+
1$
1(
1'
#20
1!
1+
0$
0(
0'
1#
1&
#30
0+
1$
1(
1'
#40
0!
1*
0)
0$
0(
0'
0#
0&
1"
1%
#50
0*
1!
1$
1(
1'
#60
1*
1!
0$
0(
0'
1#
1&
#70
0!
0*
1$
1(
1'
