2024/18feb/quesfour.v
module quesfour(
    input A,
    input SA,
    input SB,
    output Y0,
    output Y1,
    output Y2,
    output Y3
);

assign Y0 = (~SA)&&(~SB)&&A;
assign Y1 = (~SA)&&SB&&A;
assign Y2 = SA&&(~SB)&&A;
assign Y3 = SA&&SB&&A;

endmodule

2024/18feb/quesfour_tb.v
module quesfour_tb;

reg A,SA,SB;
wire Y0,Y1,Y2,Y3;

quesfour inst(
    .A(A),
    .SA(SA),
    .SB(SB),
    .Y0(Y0),
    .Y1(Y1),
    .Y2(Y2),
    .Y3(Y3)
);

initial begin
    $dumpfile("quesfour_sim.vcd");
    $dumpvars;

    SA = 0; SB = 0; A = 0; #10;
    SA = 0; SB = 0; A = 1; #10;
    SA = 0; SB = 1; A = 0; #10;
    SA = 0; SB = 1; A = 1; #10;
    SA = 1; SB = 0; A = 0; #10;
    SA = 1; SB = 0; A = 1; #10;
    SA = 1; SB = 1; A = 0; #10;
    SA = 1; SB = 1; A = 1; #10;

    $finish;

end

endmodule

2024/18feb/quesfour_sim.vcd
$date
	Mon Mar 18 11:51:31 2024
$end
$version
	Icarus Verilog
$end
$timescale
	1s
$end
$scope module quesfour_tb $end
$var wire 1 ! Y0 $end
$var wire 1 " Y1 $end
$var wire 1 # Y2 $end
$var wire 1 $ Y3 $end
$var reg 1 % A $end
$var reg 1 & SA $end
$var reg 1 ' SB $end
$scope module inst $end
$var wire 1 ( A $end
$var wire 1 ) SA $end
$var wire 1 * SB $end
$var wire 1 ! Y0 $end
$var wire 1 " Y1 $end
$var wire 1 # Y2 $end
$var wire 1 $ Y3 $end
$upscope $end
$upscope $end
$enddefinitions $end
#0
$dumpvars
0*
0)
0(
0'
0&
0%
0$
0#
0"
0!
$end
#10
1!
1%
1(
#20
0!
0%
0(
1'
1*
#30
1"
1%
1(
#40
0"
0%
0(
0'
0*
1&
1)
#50
1#
1%
1(
#60
0#
0%
0(
1'
1*
#70
1$
1%
1(
