2024/18feb/questhree.v
module questhree(
    input A,
    input B,
    input S,
    output Y
);

assign Y = (A&&(~S)) || (S&&B);

endmodule

2024/18feb/questhree_tb.v
module questhree_tb;

reg A,B,S;
wire Y;

questhree inst(
    .A(A),
    .B(B),
    .S(S),
    .Y(Y)
);

initial begin
    $dumpfile("questhree_sim.vcd");
    $dumpvars;

    S = 0; A = 0; B = 0; #10;
    S = 0; A = 0; B = 1; #10;
    S = 0; A = 1; B = 0; #10;
    S = 0; A = 1; B = 1; #10;
    S = 1; A = 0; B = 0; #10;
    S = 1; A = 0; B = 1; #10;
    S = 1; A = 1; B = 0; #10;
    S = 1; A = 1; B = 1; #10;

    $finish;
end

endmodule

2024/18feb/questhree_sim.vcd
$date
	Mon Mar 18 11:02:56 2024
$end
$version
	Icarus Verilog
$end
$timescale
	1s
$end
$scope module questhree_tb $end
$var wire 1 ! Y $end
$var reg 1 " A $end
$var reg 1 # B $end
$var reg 1 $ S $end
$scope module inst $end
$var wire 1 % A $end
$var wire 1 & B $end
$var wire 1 ' S $end
$var wire 1 ! Y $end
$upscope $end
$upscope $end
$enddefinitions $end
#0
$dumpvars
0'
0&
0%
0$
0#
0"
0!
$end
#10
1#
1&
#20
1!
0#
0&
1"
1%
#30
1#
1&
#40
0!
0#
0&
0"
0%
1$
1'
#50
1!
1#
1&
#60
0!
0#
0&
1"
1%
#70
1!
1#
1&
